django_recommend/tests.py
django_recommend/models.py
django_recommend/__init__.py
django_recommend/tasks.py
django_recommend/conf.py
django_recommend/storage.py
django_recommend/migrations/0001_initial.py
django_recommend/migrations/__init__.py
django_recommend/templatetags/__init__.py
django_recommend/templatetags/django_recommend.py
django_recommend-0.1.dev9.dist-info/RECORD
django_recommend-0.1.dev9.dist-info/top_level.txt
django_recommend-0.1.dev9.dist-info/metadata.json
django_recommend-0.1.dev9.dist-info/METADATA
django_recommend-0.1.dev9.dist-info/WHEEL
django_recommend-0.1.dev9.dist-info/DESCRIPTION.rst
