Metadata-Version: 2.0
Name: django-recommend
Version: 0.1.dev9
Summary: Generate recommendations in Django.
Home-page: https://github.com/dan-passaro/django-recommend
Author: Dan Passaro
Author-email: danpassaro@gmail.com
License: MIT
Platform: UNKNOWN
Requires-Dist: django
Requires-Dist: pyrecommend
